ratio_svenbarray/ratio.py
ratio_svenbarray-0.1.0.dist-info/METADATA
ratio_svenbarray-0.1.0.dist-info/WHEEL
ratio_svenbarray-0.1.0.dist-info/RECORD
